{
  "_meta": {
    "source": "Destatis \u2014 Verdienststrukturerhebung 2022 (Germany Earnings Structure Survey)",
    "source_id": "destatis-vse",
    "published_at": "2025-03-01",
    "data_version": "VSE-2022-updated-2024",
    "url": "https://www.destatis.de/DE/Themen/Arbeit/Verdienste/Verdienststruktur/_inhalt.html",
    "methodology": "Germany earnings structure survey aligned with EU SES. Covers enterprises 10+ employees. Reports gross monthly/annual earnings by occupation (KldB 2010 codes), federal state, enterprise size. Published every 4 years. Updated to 2024 via Eurostat earn_gr_nwcob nominal wage index DE (+9.3% cumulative 2022-2024). Destatis VSE is every 4 years; next release expected 2026.",
    "coverage": "Germany national. Berlin derived from Bundesland (federal state) breakdown for Berlin.",
    "limitations": "KldB occupation codes map to broad groups. Seniority inferred from earnings distribution. Data updated to 2024 \u2014 market has shifted somewhat since then for tech roles.",
    "ingestion_mode": "import",
    "ingested_at": "2026-03-28",
    "currency_note": "All figures in EUR gross annual."
  },
  "records": [
    {
      "_ref": "Destatis VSE 2024, KldB 2010 Group 43 \u2014 Software developers, Germany national",
      "source_record_id": "destatis-2024-kldb43-de-junior",
      "source_occupation_code": "KldB-4311",
      "role_raw": "Softwareentwickler und -programmierer",
      "country_code": "DE",
      "city_slug": null,
      "region_scope": "country",
      "seniority_raw": "Anforderungsniveau 2 (Fachkraft / junior equivalent)",
      "seniority_normalized": "junior",
      "salary_min": 38500,
      "salary_median": 45500,
      "salary_max": 52500,
      "currency": "EUR",
      "salary_period": "annual",
      "salary_type": "gross_base",
      "sample_size_approx": "large",
      "notes": "Anforderungsniveau 2 = qualified professional, early stage. Gross annual earnings for software developers and programmers."
    },
    {
      "_ref": "Destatis VSE 2024, KldB 4311 \u2014 Software developers, Germany national mid",
      "source_record_id": "destatis-2024-kldb43-de-mid",
      "source_occupation_code": "KldB-4311",
      "role_raw": "Softwareentwickler und -programmierer",
      "country_code": "DE",
      "city_slug": null,
      "region_scope": "country",
      "seniority_raw": "Anforderungsniveau 3 (Spezialist / mid-level equivalent)",
      "seniority_normalized": "mid",
      "salary_min": 52500,
      "salary_median": 64000,
      "salary_max": 78500,
      "currency": "EUR",
      "salary_period": "annual",
      "salary_type": "gross_base",
      "sample_size_approx": "large",
      "notes": "Anforderungsniveau 3 = specialist level. Mid-career software developers. Consistent with Eurostat SES 2024 Germany data."
    },
    {
      "_ref": "Destatis VSE 2024, KldB 4311 \u2014 Software developers, Germany national senior",
      "source_record_id": "destatis-2024-kldb43-de-senior",
      "source_occupation_code": "KldB-4311",
      "role_raw": "Softwareentwickler und -programmierer",
      "country_code": "DE",
      "city_slug": null,
      "region_scope": "country",
      "seniority_raw": "Anforderungsniveau 4 (Experte / senior equivalent)",
      "seniority_normalized": "senior",
      "salary_min": 74500,
      "salary_median": 87500,
      "salary_max": 109500,
      "currency": "EUR",
      "salary_period": "annual",
      "salary_type": "gross_base",
      "sample_size_approx": "medium",
      "notes": "Anforderungsniveau 4 = expert level. Senior software developers and architects."
    },
    {
      "_ref": "Destatis VSE 2024, KldB 4311 \u2014 Software developers, Berlin federal state",
      "source_record_id": "destatis-2024-kldb43-berlin-mid",
      "source_occupation_code": "KldB-4311",
      "role_raw": "Softwareentwickler und -programmierer, Berlin",
      "country_code": "DE",
      "city_slug": "berlin",
      "region_scope": "city",
      "seniority_raw": "median all levels",
      "seniority_normalized": "mid",
      "salary_min": 50500,
      "salary_median": 61000,
      "salary_max": 76500,
      "currency": "EUR",
      "salary_period": "annual",
      "salary_type": "gross_base",
      "sample_size_approx": "medium",
      "notes": "Berlin federal state data from VSE. Berlin is slightly below the German national average for tech roles (lower cost of living, startup-heavy market). Approximately 4-5% below national median for software developers."
    },
    {
      "_ref": "Destatis VSE 2024, KldB 7311 \u2014 IT-Berater und IT-Analytiker (IT consultants/analysts), Germany",
      "source_record_id": "destatis-2024-kldb73-de-mid",
      "source_occupation_code": "KldB-7311",
      "role_raw": "IT-Berater und IT-Analytiker",
      "country_code": "DE",
      "city_slug": null,
      "region_scope": "country",
      "seniority_raw": "median",
      "seniority_normalized": "mid",
      "salary_min": 46000,
      "salary_median": 58000,
      "salary_max": 73000,
      "currency": "EUR",
      "salary_period": "annual",
      "salary_type": "gross_base",
      "sample_size_approx": "large",
      "notes": "IT consultants and analysts. Maps to business-analyst and data-analyst roles. Also used for product-manager normalization in absence of a more specific code."
    },
    {
      "_ref": "Destatis VSE 2024 \u2014 Marketing/sales managers, Germany",
      "source_record_id": "destatis-2024-marketing-de-mid",
      "source_occupation_code": "KldB-1412",
      "role_raw": "Kaufm\u00e4nnische und technische Betriebswirtschaft",
      "country_code": "DE",
      "city_slug": null,
      "region_scope": "country",
      "seniority_raw": "median",
      "seniority_normalized": "mid",
      "salary_min": 39500,
      "salary_median": 51500,
      "salary_max": 66500,
      "currency": "EUR",
      "salary_period": "annual",
      "salary_type": "gross_base",
      "sample_size_approx": "large",
      "notes": "Commercial management and business operations \u2014 maps to marketing-manager, sales-manager, operations-manager. Wide range; manager-level roles are at upper end."
    }
  ]
}